LICENSE
README.md
setup.py
bin/cfr
cfr/__init__.py
cfr/climate.py
cfr/gcm.py
cfr/ml.py
cfr/proxy.py
cfr/psm.py
cfr/reconjob.py
cfr/reconres.py
cfr/ts.py
cfr/utils.py
cfr/visual.py
cfr.egg-info/PKG-INFO
cfr.egg-info/SOURCES.txt
cfr.egg-info/dependency_links.txt
cfr.egg-info/not-zip-safe
cfr.egg-info/requires.txt
cfr.egg-info/top_level.txt
cfr/da/__init__.py
cfr/da/enkf.py