Metadata-Version: 2.4
Name: cfr
Version: 2026.1.31
Summary: cfr: a Python package for Climate Field Reconstruction
Home-page: https://github.com/fzhu2e/cfr
Author: Feng Zhu, Julien Emile-Geay
Author-email: fengzhu@ucar.edu, julieneg@usc.edu
License: BSD 3-Clause
Keywords: climate field reconstruction
Classifier: Natural Language :: English
Classifier: Programming Language :: Python :: 3.11
Classifier: Programming Language :: Python :: 3.12
Classifier: Programming Language :: Python :: 3.13
License-File: LICENSE
Requires-Dist: colorama
Requires-Dist: seaborn
Requires-Dist: pandas
Requires-Dist: tqdm
Requires-Dist: xarray
Requires-Dist: netCDF4
Requires-Dist: nc-time-axis
Requires-Dist: dask
Requires-Dist: statsmodels
Requires-Dist: eofs
Requires-Dist: plotly
Requires-Dist: pyresample
Provides-Extra: psm
Requires-Dist: pathos; extra == "psm"
Requires-Dist: fbm; extra == "psm"
Provides-Extra: ml
Requires-Dist: scikit-learn; extra == "ml"
Requires-Dist: torch; extra == "ml"
Requires-Dist: torchvision; extra == "ml"
Provides-Extra: graphem
Requires-Dist: cython; extra == "graphem"
Requires-Dist: scikit-learn; extra == "graphem"
Requires-Dist: cfr-graphem; extra == "graphem"
Dynamic: author
Dynamic: author-email
Dynamic: classifier
Dynamic: description
Dynamic: description-content-type
Dynamic: home-page
Dynamic: keywords
Dynamic: license
Dynamic: license-file
Dynamic: provides-extra
Dynamic: requires-dist
Dynamic: summary
